_databind_json_proxy/__init__.py
databind.json-4.5.1.dist-info/WHEEL
databind.json-4.5.1.dist-info/METADATA
databind.json-4.5.1.dist-info/RECORD
